pydantic_vault/__init__.py
pydantic_vault/py.typed
pydantic_vault/vault_settings.py
pydantic_vault-1.0.0.dist-info/LICENSE
pydantic_vault-1.0.0.dist-info/METADATA
pydantic_vault-1.0.0.dist-info/WHEEL
pydantic_vault-1.0.0.dist-info/RECORD
