Metadata-Version: 2.1
Name: pydantic-vault
Version: 1.0.0
Summary: A simple extension to Pydantic BaseSettings that can retrieve secrets from Hashicorp Vault
Home-page: https://github.com/nymous/pydantic-vault
License: MIT
Keywords: hashicorp,vault,hvac,pydantic
Author: Thomas Gaudin
Author-email: thomas.gaudin@centraliens-lille.org
Requires-Python: >=3.7,<4.0
Classifier: Development Status :: 4 - Beta
Classifier: Intended Audience :: Developers
Classifier: Intended Audience :: Information Technology
Classifier: Intended Audience :: System Administrators
Classifier: License :: OSI Approved :: MIT License
Classifier: Programming Language :: Python :: 3
Classifier: Programming Language :: Python :: 3.7
Classifier: Programming Language :: Python :: 3.8
Classifier: Programming Language :: Python :: 3.9
Classifier: Programming Language :: Python :: 3.10
Classifier: Programming Language :: Python :: 3.11
Classifier: Programming Language :: Python :: 3 :: Only
Classifier: Topic :: Internet
Classifier: Topic :: Security
Classifier: Topic :: Software Development
Classifier: Topic :: Software Development :: Libraries
Classifier: Topic :: Software Development :: Libraries :: Python Modules
Classifier: Typing :: Typed
Requires-Dist: hvac (>=0.10.6)
Requires-Dist: pydantic (>=1.8,<2.0)
Project-URL: Bug Tracker, https://github.com/nymous/pydantic-vault/issues
Project-URL: Changelog, https://github.com/nymous/pydantic-vault/blob/master/CHANGELOG.md
Project-URL: Documentation, https://github.com/nymous/pydantic-vault
Project-URL: Repository, https://github.com/nymous/pydantic-vault
